[{"id": 1, "ts": "2026-04-15T22:48:54", "scan_date": "2026-04-15", "symbol": "APLS", "setup_type": "breakout", "status": "ready", "score": 1.0, "metrics": {"avance_3m": 1.0090999200189517, "contraccion_10d": 0.01371040167841071, "dist_ema10": 0.06905920491486106}, "guidance": [], "acted": 0}, {"id": 2, "ts": "2026-04-15T22:48:54", "scan_date": "2026-04-15", "symbol": "CWEN-A", "setup_type": "breakout", "status": "ready", "score": 1.0, "metrics": {"avance_3m": 0.309928024023717, "contraccion_10d": 0.05289290363063121, "dist_ema10": 0.0070872243408504065}, "guidance": [], "acted": 0}, {"id": 37, "ts": "2026-04-15T22:48:54", "scan_date": "2026-04-15", "symbol": "AUR", "setup_type": "parabolic", "status": "ready", "score": 1.0, "metrics": {"avance_10d": 0.26794268143340916, "avance_5d": 0.31513645528740786, "dist_ema10": 0.18953921507255744, "dias_up": 7.0, "racha_max": 4.0}, "guidance": [], "acted": 0}, {"id": 38, "ts": "2026-04-15T22:48:54", "scan_date": "2026-04-15", "symbol": "CAR", "setup_type": "parabolic", "status": "ready", "score": 1.0, "metrics": {"avance_10d": 1.3271004408154243, "avance_5d": 0.3322001040194593, "dist_ema10": 0.3090555099351946, "dias_up": 9.0, "racha_max": 10.0}, "guidance": [], "acted": 0}, {"id": 45, "ts": "2026-04-15T22:48:55", "scan_date": "2026-04-15", "symbol": "TGT", "setup_type": "vcp", "status": "ready", "score": 0.93, "metrics": {"avance_previo": 0.39, "t1_pullback": 0.0858, "t2_pullback": 0.0699, "t3_pullback": 0.0606, "vol_drying_ratio": 0.69, "pct_from_pivot": -0.0248, "final_tightness": 0.0621, "base_days": 30}, "guidance": [], "acted": 0}, {"id": 39, "ts": "2026-04-15T22:48:54", "scan_date": "2026-04-15", "symbol": "AVGO", "setup_type": "parabolic", "status": "ready", "score": 0.9, "metrics": {"avance_10d": 0.2654949554341519, "avance_5d": 0.11780450572590451, "dist_ema10": 0.1044214822723708, "dias_up": 9.0, "racha_max": 7.0}, "guidance": ["Impulso corto plazo flojo (avance 5d 11.8%, objetivo >=15%)."], "acted": 0}, {"id": 40, "ts": "2026-04-15T22:48:55", "scan_date": "2026-04-15", "symbol": "INTC", "setup_type": "parabolic", "status": "ready", "score": 0.9, "metrics": {"avance_10d": 0.3520717070973227, "avance_5d": 0.05217111401519259, "dist_ema10": 0.10526830464075343, "dias_up": 9.0, "racha_max": 9.0}, "guidance": ["Impulso corto plazo flojo (avance 5d 5.2%, objetivo >=15%)."], "acted": 0}, {"id": 41, "ts": "2026-04-15T22:48:55", "scan_date": "2026-04-15", "symbol": "MRVL", "setup_type": "parabolic", "status": "ready", "score": 0.9, "metrics": {"avance_10d": 0.2619940563796277, "avance_5d": 0.1228832200412433, "dist_ema10": 0.1124045296773355, "dias_up": 9.0, "racha_max": 6.0}, "guidance": ["Impulso corto plazo flojo (avance 5d 12.3%, objetivo >=15%)."], "acted": 0}, {"id": 42, "ts": "2026-04-15T22:48:55", "scan_date": "2026-04-15", "symbol": "AMKR", "setup_type": "parabolic", "status": "ready", "score": 0.9, "metrics": {"avance_10d": 0.2845773083369061, "avance_5d": 0.08306133263966808, "dist_ema10": 0.08617927869654696, "dias_up": 9.0, "racha_max": 10.0}, "guidance": ["Impulso corto plazo flojo (avance 5d 8.3%, objetivo >=15%)."], "acted": 0}, {"id": 46, "ts": "2026-04-15T22:48:55", "scan_date": "2026-04-15", "symbol": "FDX", "setup_type": "vcp", "status": "ready", "score": 0.86, "metrics": {"avance_previo": 0.445, "t1_pullback": 0.1157, "t2_pullback": 0.1072, "t3_pullback": 0.0914, "vol_drying_ratio": 0.75, "pct_from_pivot": -0.0674, "final_tightness": 0.0535, "base_days": 33}, "guidance": ["A 6.7% del pivot. Acercandose."], "acted": 0}, {"id": 47, "ts": "2026-04-15T22:48:55", "scan_date": "2026-04-15", "symbol": "HAL", "setup_type": "vcp", "status": "ready", "score": 0.83, "metrics": {"avance_previo": 0.464, "t1_pullback": 0.086, "t2_pullback": 0.0658, "t3_pullback": 0.0355, "vol_drying_ratio": 0.86, "pct_from_pivot": -0.0884, "final_tightness": 0.0389, "base_days": 12}, "guidance": ["Volumen bajando pero no lo suficiente.", "A 8.8% del pivot. Acercandose."], "acted": 0}, {"id": 48, "ts": "2026-04-15T22:48:55", "scan_date": "2026-04-15", "symbol": "HWM", "setup_type": "vcp", "status": "ready", "score": 0.83, "metrics": {"avance_previo": 0.363, "t1_pullback": 0.129, "t2_pullback": 0.0668, "t3_pullback": 0.1379, "vol_drying_ratio": 0.73, "pct_from_pivot": -0.0496, "final_tightness": 0.0416, "base_days": 32}, "guidance": ["Solo 2 contracciones detectadas; ideal son 3."], "acted": 0}, {"id": 49, "ts": "2026-04-15T22:48:56", "scan_date": "2026-04-15", "symbol": "ADI", "setup_type": "vcp", "status": "ready", "score": 0.8, "metrics": {"avance_previo": 0.413, "t1_pullback": 0.1515, "t2_pullback": 0.0753, "t3_pullback": 0.1484, "vol_drying_ratio": 0.81, "pct_from_pivot": -0.039, "final_tightness": 0.0373, "base_days": 35}, "guidance": ["Solo 2 contracciones detectadas; ideal son 3.", "Volumen bajando pero no lo suficiente."], "acted": 0}, {"id": 50, "ts": "2026-04-15T22:48:57", "scan_date": "2026-04-15", "symbol": "DVA", "setup_type": "vcp", "status": "near", "score": 0.76, "metrics": {"avance_previo": 0.338, "t1_pullback": 0.0836, "t2_pullback": 0.0591, "t3_pullback": 0.0664, "vol_drying_ratio": 0.66, "pct_from_pivot": -0.0932, "final_tightness": 0.0615, "base_days": 32}, "guidance": ["Solo 2 contracciones detectadas; ideal son 3.", "A 9.3% del pivot. Acercandose."], "acted": 0}, {"id": 51, "ts": "2026-04-15T22:48:57", "scan_date": "2026-04-15", "symbol": "ODFL", "setup_type": "vcp", "status": "near", "score": 0.76, "metrics": {"avance_previo": 0.446, "t1_pullback": 0.2057, "t2_pullback": 0.0809, "t3_pullback": 0.0792, "vol_drying_ratio": 0.79, "pct_from_pivot": -0.0742, "final_tightness": 0.0424, "base_days": 30}, "guidance": ["Volumen bajando pero no lo suficiente.", "A 7.4% del pivot. Acercandose."], "acted": 0}, {"id": 52, "ts": "2026-04-15T22:48:57", "scan_date": "2026-04-15", "symbol": "TPR", "setup_type": "vcp", "status": "near", "score": 0.76, "metrics": {"avance_previo": 0.487, "t1_pullback": 0.1466, "t2_pullback": 0.0759, "t3_pullback": 0.1117, "vol_drying_ratio": 0.69, "pct_from_pivot": -0.0629, "final_tightness": 0.0448, "base_days": 34}, "guidance": ["Solo 2 contracciones detectadas; ideal son 3.", "A 6.3% del pivot. Acercandose."], "acted": 0}, {"id": 53, "ts": "2026-04-15T22:48:57", "scan_date": "2026-04-15", "symbol": "MU", "setup_type": "vcp", "status": "near", "score": 0.75, "metrics": {"avance_previo": 0.897, "t1_pullback": 0.2121, "t2_pullback": 0.1409, "t3_pullback": 0.1333, "vol_drying_ratio": 0.78, "pct_from_pivot": -0.0317, "final_tightness": 0.1476, "base_days": 20}, "guidance": ["Volumen bajando pero no lo suficiente.", "Consolidacion final amplia (14.8%, objetivo <=4%)."], "acted": 0}, {"id": 54, "ts": "2026-04-15T22:48:57", "scan_date": "2026-04-15", "symbol": "CAVA", "setup_type": "vcp", "status": "near", "score": 0.75, "metrics": {"avance_previo": 0.639, "t1_pullback": 0.1387, "t2_pullback": 0.1177, "t3_pullback": 0.1332, "vol_drying_ratio": 0.68, "pct_from_pivot": -0.037, "final_tightness": 0.0788, "base_days": 20}, "guidance": ["Solo 2 contracciones detectadas; ideal son 3.", "Consolidacion final amplia (7.9%, objetivo <=4%)."], "acted": 0}, {"id": 55, "ts": "2026-04-15T22:48:57", "scan_date": "2026-04-15", "symbol": "CFG", "setup_type": "vcp", "status": "near", "score": 0.73, "metrics": {"avance_previo": 0.34, "t1_pullback": 0.1483, "t2_pullback": 0.0736, "t3_pullback": 0.1185, "vol_drying_ratio": 0.8, "pct_from_pivot": -0.0523, "final_tightness": 0.0362, "base_days": 44}, "guidance": ["Solo 2 contracciones detectadas; ideal son 3.", "Volumen bajando pero no lo suficiente.", "A 5.2% del pivot. Acercandose."], "acted": 0}, {"id": 56, "ts": "2026-04-15T22:48:57", "scan_date": "2026-04-15", "symbol": "EME", "setup_type": "vcp", "status": "near", "score": 0.73, "metrics": {"avance_previo": 0.348, "t1_pullback": 0.1489, "t2_pullback": 0.0991, "t3_pullback": 0.1537, "vol_drying_ratio": 0.83, "pct_from_pivot": -0.0376, "final_tightness": 0.0421, "base_days": 43}, "guidance": ["Solo 2 contracciones detectadas; ideal son 3.", "Volumen bajando pero no lo suficiente."], "acted": 0}, {"id": 57, "ts": "2026-04-15T22:48:57", "scan_date": "2026-04-15", "symbol": "IRM", "setup_type": "vcp", "status": "near", "score": 0.73, "metrics": {"avance_previo": 0.351, "t1_pullback": 0.1104, "t2_pullback": 0.0889, "t3_pullback": 0.1313, "vol_drying_ratio": 0.89, "pct_from_pivot": -0.0066, "final_tightness": 0.0658, "base_days": 35}, "guidance": ["Solo 2 contracciones detectadas; ideal son 3.", "Volumen bajando pero no lo suficiente."], "acted": 0}, {"id": 58, "ts": "2026-04-15T22:48:57", "scan_date": "2026-04-15", "symbol": "KEY", "setup_type": "vcp", "status": "near", "score": 0.73, "metrics": {"avance_previo": 0.306, "t1_pullback": 0.1306, "t2_pullback": 0.0874, "t3_pullback": 0.1073, "vol_drying_ratio": 0.9, "pct_from_pivot": -0.0671, "final_tightness": 0.0297, "base_days": 46}, "guidance": ["Solo 2 contracciones detectadas; ideal son 3.", "Volumen bajando pero no lo suficiente.", "A 6.7% del pivot. Acercandose."], "acted": 0}, {"id": 59, "ts": "2026-04-15T22:48:57", "scan_date": "2026-04-15", "symbol": "NUE", "setup_type": "vcp", "status": "near", "score": 0.73, "metrics": {"avance_previo": 0.355, "t1_pullback": 0.1301, "t2_pullback": 0.1236, "t3_pullback": 0.1545, "vol_drying_ratio": 0.87, "pct_from_pivot": -0.0338, "final_tightness": 0.0546, "base_days": 44}, "guidance": ["Solo 2 contracciones detectadas; ideal son 3.", "Volumen bajando pero no lo suficiente."], "acted": 0}, {"id": 60, "ts": "2026-04-15T22:48:57", "scan_date": "2026-04-15", "symbol": "SLB", "setup_type": "vcp", "status": "near", "score": 0.73, "metrics": {"avance_previo": 0.436, "t1_pullback": 0.1088, "t2_pullback": 0.0677, "t3_pullback": 0.0518, "vol_drying_ratio": 0.9, "pct_from_pivot": -0.0434, "final_tightness": 0.0542, "base_days": 12}, "guidance": ["Volumen no se seca (ratio 0.90, objetivo <=0.75)."], "acted": 0}, {"id": 61, "ts": "2026-04-15T22:48:57", "scan_date": "2026-04-15", "symbol": "TXN", "setup_type": "vcp", "status": "near", "score": 0.73, "metrics": {"avance_previo": 0.435, "t1_pullback": 0.1278, "t2_pullback": 0.0882, "t3_pullback": 0.1399, "vol_drying_ratio": 0.86, "pct_from_pivot": -0.065, "final_tightness": 0.0398, "base_days": 44}, "guidance": ["Solo 2 contracciones detectadas; ideal son 3.", "Volumen bajando pero no lo suficiente.", "A 6.5% del pivot. Acercandose."], "acted": 0}, {"id": 43, "ts": "2026-04-15T22:48:55", "scan_date": "2026-04-15", "symbol": "SNDK", "setup_type": "parabolic", "status": "near", "score": 0.7, "metrics": {"avance_10d": 0.2872547685892335, "avance_5d": 0.04714816519321108, "dist_ema10": 0.07559023051671776, "dias_up": 7.0, "racha_max": 4.0}, "guidance": ["Necesita alejarse de EMA10 (actual 7.6%, objetivo >=8%).", "Impulso corto plazo flojo (avance 5d 4.7%, objetivo >=15%)."], "acted": 0}, {"id": 62, "ts": "2026-04-15T22:48:57", "scan_date": "2026-04-15", "symbol": "BKR", "setup_type": "vcp", "status": "near", "score": 0.7, "metrics": {"avance_previo": 0.359, "t1_pullback": 0.1928, "t2_pullback": 0.1555, "t3_pullback": 0.0857, "vol_drying_ratio": 0.65, "pct_from_pivot": -0.1034, "final_tightness": 0.0832, "base_days": 32}, "guidance": ["Lejos del pivot (-10.3% del maximo).", "Consolidacion final amplia (8.3%, objetivo <=4%)."], "acted": 0}, {"id": 63, "ts": "2026-04-15T22:48:57", "scan_date": "2026-04-15", "symbol": "COKE", "setup_type": "vcp", "status": "near", "score": 0.7, "metrics": {"avance_previo": 0.35, "t1_pullback": 0.1896, "t2_pullback": 0.119, "t3_pullback": 0.0887, "vol_drying_ratio": 0.73, "pct_from_pivot": -0.1466, "final_tightness": 0.1346, "base_days": 22}, "guidance": ["Lejos del pivot (-14.7% del maximo).", "Consolidacion final amplia (13.5%, objetivo <=4%)."], "acted": 0}, {"id": 64, "ts": "2026-04-15T22:48:57", "scan_date": "2026-04-15", "symbol": "ALB", "setup_type": "vcp", "status": "near", "score": 0.68, "metrics": {"avance_previo": 0.628, "t1_pullback": 0.2366, "t2_pullback": 0.1439, "t3_pullback": 0.0928, "vol_drying_ratio": 0.85, "pct_from_pivot": -0.0979, "final_tightness": 0.1086, "base_days": 35}, "guidance": ["Volumen bajando pero no lo suficiente.", "A 9.8% del pivot. Acercandose.", "Consolidacion final amplia (10.9%, objetivo <=4%)."], "acted": 0}, {"id": 65, "ts": "2026-04-15T22:48:57", "scan_date": "2026-04-15", "symbol": "MRNA", "setup_type": "vcp", "status": "near", "score": 0.68, "metrics": {"avance_previo": 1.336, "t1_pullback": 0.1735, "t2_pullback": 0.1266, "t3_pullback": 0.131, "vol_drying_ratio": 0.57, "pct_from_pivot": -0.0888, "final_tightness": 0.0955, "base_days": 30}, "guidance": ["Solo 2 contracciones detectadas; ideal son 3.", "A 8.9% del pivot. Acercandose.", "Consolidacion final amplia (9.5%, objetivo <=4%)."], "acted": 0}, {"id": 66, "ts": "2026-04-15T22:48:57", "scan_date": "2026-04-15", "symbol": "VTRS", "setup_type": "vcp", "status": "near", "score": 0.68, "metrics": {"avance_previo": 0.541, "t1_pullback": 0.166, "t2_pullback": 0.0576, "t3_pullback": 0.0692, "vol_drying_ratio": 0.56, "pct_from_pivot": -0.1513, "final_tightness": 0.0455, "base_days": 34}, "guidance": ["Solo 2 contracciones detectadas; ideal son 3.", "Lejos del pivot (-15.1% del maximo)."], "acted": 0}, {"id": 67, "ts": "2026-04-15T22:48:57", "scan_date": "2026-04-15", "symbol": "CGNX", "setup_type": "vcp", "status": "near", "score": 0.68, "metrics": {"avance_previo": 0.629, "t1_pullback": 0.1378, "t2_pullback": 0.1007, "t3_pullback": 0.1828, "vol_drying_ratio": 0.59, "pct_from_pivot": -0.0862, "final_tightness": 0.0714, "base_days": 43}, "guidance": ["Solo 2 contracciones detectadas; ideal son 3.", "A 8.6% del pivot. Acercandose.", "Consolidacion final amplia (7.1%, objetivo <=4%)."], "acted": 0}, {"id": 68, "ts": "2026-04-15T22:48:57", "scan_date": "2026-04-15", "symbol": "ECG", "setup_type": "vcp", "status": "near", "score": 0.68, "metrics": {"avance_previo": 0.517, "t1_pullback": 0.2217, "t2_pullback": 0.1088, "t3_pullback": 0.1977, "vol_drying_ratio": 0.65, "pct_from_pivot": -0.0659, "final_tightness": 0.0834, "base_days": 35}, "guidance": ["Solo 2 contracciones detectadas; ideal son 3.", "A 6.6% del pivot. Acercandose.", "Consolidacion final amplia (8.3%, objetivo <=4%)."], "acted": 0}, {"id": 69, "ts": "2026-04-15T22:48:57", "scan_date": "2026-04-15", "symbol": "VLO", "setup_type": "vcp", "status": "near", "score": 0.66, "metrics": {"avance_previo": 0.597, "t1_pullback": 0.088, "t2_pullback": 0.0877, "t3_pullback": 0.0507, "vol_drying_ratio": 0.97, "pct_from_pivot": -0.0907, "final_tightness": 0.0654, "base_days": 12}, "guidance": ["Volumen no se seca (ratio 0.97, objetivo <=0.75).", "A 9.1% del pivot. Acercandose."], "acted": 0}, {"id": 3, "ts": "2026-04-15T22:48:54", "scan_date": "2026-04-15", "symbol": "AMAT", "setup_type": "breakout", "status": "near", "score": 0.65, "metrics": {"avance_3m": 0.307601105666897, "contraccion_10d": 0.1776492842542119, "dist_ema10": 0.03353525762586651}, "guidance": ["Base todavia amplia (contraccion 17.8%, objetivo <=7%)."], "acted": 0}, {"id": 4, "ts": "2026-04-15T22:48:54", "scan_date": "2026-04-15", "symbol": "CIEN", "setup_type": "breakout", "status": "near", "score": 0.65, "metrics": {"avance_3m": 0.9958050172853565, "contraccion_10d": 0.23892294555432225, "dist_ema10": 0.031408234726668205}, "guidance": ["Base todavia amplia (contraccion 23.9%, objetivo <=7%)."], "acted": 0}, {"id": 5, "ts": "2026-04-15T22:48:54", "scan_date": "2026-04-15", "symbol": "COHR", "setup_type": "breakout", "status": "near", "score": 0.65, "metrics": {"avance_3m": 0.6739993003384019, "contraccion_10d": 0.29425702176570623, "dist_ema10": 0.07048279644575484}, "guidance": ["Base todavia amplia (contraccion 29.4%, objetivo <=7%)."], "acted": 0}, {"id": 6, "ts": "2026-04-15T22:48:54", "scan_date": "2026-04-15", "symbol": "EQIX", "setup_type": "breakout", "status": "near", "score": 0.65, "metrics": {"avance_3m": 0.3250219275002342, "contraccion_10d": 0.07792163980295877, "dist_ema10": 0.023761282001491857}, "guidance": ["Base todavia amplia (contraccion 7.8%, objetivo <=7%)."], "acted": 0}, {"id": 7, "ts": "2026-04-15T22:48:54", "scan_date": "2026-04-15", "symbol": "FIX", "setup_type": "breakout", "status": "near", "score": 0.65, "metrics": {"avance_3m": 0.5666285803354845, "contraccion_10d": 0.1843282786557578, "dist_ema10": 0.06143905277182937}, "guidance": ["Base todavia amplia (contraccion 18.4%, objetivo <=7%)."], "acted": 0}, {"id": 8, "ts": "2026-04-15T22:48:54", "scan_date": "2026-04-15", "symbol": "GEV", "setup_type": "breakout", "status": "near", "score": 0.65, "metrics": {"avance_3m": 0.5314293401689649, "contraccion_10d": 0.1434497678587668, "dist_ema10": 0.035629471054702266}, "guidance": ["Base todavia amplia (contraccion 14.3%, objetivo <=7%)."], "acted": 0}, {"id": 9, "ts": "2026-04-15T22:48:54", "scan_date": "2026-04-15", "symbol": "GLW", "setup_type": "breakout", "status": "near", "score": 0.65, "metrics": {"avance_3m": 0.8687957222085994, "contraccion_10d": 0.2400902886474594, "dist_ema10": 0.03922679166973575}, "guidance": ["Base todavia amplia (contraccion 24.0%, objetivo <=7%)."], "acted": 0}, {"id": 10, "ts": "2026-04-15T22:48:54", "scan_date": "2026-04-15", "symbol": "INTC", "setup_type": "breakout", "status": "near", "score": 0.65, "metrics": {"avance_3m": 0.33292284101607494, "contraccion_10d": 0.3212195258920071, "dist_ema10": 0.10526830464075343}, "guidance": ["Base todavia amplia (contraccion 32.1%, objetivo <=7%)."], "acted": 0}, {"id": 11, "ts": "2026-04-15T22:48:54", "scan_date": "2026-04-15", "symbol": "KEYS", "setup_type": "breakout", "status": "near", "score": 0.65, "metrics": {"avance_3m": 0.5532474187214418, "contraccion_10d": 0.1672282589114143, "dist_ema10": 0.03199396646183805}, "guidance": ["Base todavia amplia (contraccion 16.7%, objetivo <=7%)."], "acted": 0}, {"id": 12, "ts": "2026-04-15T22:48:54", "scan_date": "2026-04-15", "symbol": "MPWR", "setup_type": "breakout", "status": "near", "score": 0.65, "metrics": {"avance_3m": 0.37830935699337953, "contraccion_10d": 0.22665190996281412, "dist_ema10": 0.05516496266348425}, "guidance": ["Base todavia amplia (contraccion 22.7%, objetivo <=7%)."], "acted": 0}, {"id": 13, "ts": "2026-04-15T22:48:54", "scan_date": "2026-04-15", "symbol": "MRNA", "setup_type": "breakout", "status": "near", "score": 0.65, "metrics": {"avance_3m": 0.33711177607709253, "contraccion_10d": 0.14380762339080197, "dist_ema10": 0.04911663431178592}, "guidance": ["Base todavia amplia (contraccion 14.4%, objetivo <=7%)."], "acted": 0}, {"id": 14, "ts": "2026-04-15T22:48:54", "scan_date": "2026-04-15", "symbol": "MU", "setup_type": "breakout", "status": "near", "score": 0.65, "metrics": {"avance_3m": 0.369196545426137, "contraccion_10d": 0.2752558655682756, "dist_ema10": 0.08763594902298788}, "guidance": ["Base todavia amplia (contraccion 27.5%, objetivo <=7%)."], "acted": 0}, {"id": 15, "ts": "2026-04-15T22:48:54", "scan_date": "2026-04-15", "symbol": "PWR", "setup_type": "breakout", "status": "near", "score": 0.65, "metrics": {"avance_3m": 0.35432827922040055, "contraccion_10d": 0.08786455232412017, "dist_ema10": 0.02109307782337555}, "guidance": ["Base todavia amplia (contraccion 8.8%, objetivo <=7%)."], "acted": 0}, {"id": 16, "ts": "2026-04-15T22:48:54", "scan_date": "2026-04-15", "symbol": "STX", "setup_type": "breakout", "status": "near", "score": 0.65, "metrics": {"avance_3m": 0.66679380031585, "contraccion_10d": 0.26543492954292, "dist_ema10": 0.06677576007722141}, "guidance": ["Base todavia amplia (contraccion 26.5%, objetivo <=7%)."], "acted": 0}, {"id": 17, "ts": "2026-04-15T22:48:54", "scan_date": "2026-04-15", "symbol": "TER", "setup_type": "breakout", "status": "near", "score": 0.65, "metrics": {"avance_3m": 0.5861357331415842, "contraccion_10d": 0.22742218857766558, "dist_ema10": 0.0480565173878611}, "guidance": ["Base todavia amplia (contraccion 22.7%, objetivo <=7%)."], "acted": 0}, {"id": 18, "ts": "2026-04-15T22:48:54", "scan_date": "2026-04-15", "symbol": "VRT", "setup_type": "breakout", "status": "near", "score": 0.65, "metrics": {"avance_3m": 0.7630321245983744, "contraccion_10d": 0.21432128232194625, "dist_ema10": 0.05146879914437452}, "guidance": ["Base todavia amplia (contraccion 21.4%, objetivo <=7%)."], "acted": 0}, {"id": 19, "ts": "2026-04-15T22:48:54", "scan_date": "2026-04-15", "symbol": "WDC", "setup_type": "breakout", "status": "near", "score": 0.65, "metrics": {"avance_3m": 0.6984870024132497, "contraccion_10d": 0.24191777477525686, "dist_ema10": 0.08793920335970307}, "guidance": ["Base todavia amplia (contraccion 24.2%, objetivo <=7%)."], "acted": 0}, {"id": 20, "ts": "2026-04-15T22:48:54", "scan_date": "2026-04-15", "symbol": "ARM", "setup_type": "breakout", "status": "near", "score": 0.65, "metrics": {"avance_3m": 0.5176683453660347, "contraccion_10d": 0.16267101019621152, "dist_ema10": 0.04420583596383243}, "guidance": ["Base todavia amplia (contraccion 16.3%, objetivo <=7%)."], "acted": 0}, {"id": 21, "ts": "2026-04-15T22:48:54", "scan_date": "2026-04-15", "symbol": "MRVL", "setup_type": "breakout", "status": "near", "score": 0.65, "metrics": {"avance_3m": 0.6582611705896899, "contraccion_10d": 0.28038834720301187, "dist_ema10": 0.1124045296773355}, "guidance": ["Base todavia amplia (contraccion 28.0%, objetivo <=7%)."], "acted": 0}, {"id": 22, "ts": "2026-04-15T22:48:54", "scan_date": "2026-04-15", "symbol": "ARW", "setup_type": "breakout", "status": "near", "score": 0.65, "metrics": {"avance_3m": 0.4567241010994747, "contraccion_10d": 0.21842824355151802, "dist_ema10": 0.05554747616219413}, "guidance": ["Base todavia amplia (contraccion 21.8%, objetivo <=7%)."], "acted": 0}, {"id": 23, "ts": "2026-04-15T22:48:54", "scan_date": "2026-04-15", "symbol": "AVT", "setup_type": "breakout", "status": "near", "score": 0.65, "metrics": {"avance_3m": 0.4113037538747548, "contraccion_10d": 0.1828539411004668, "dist_ema10": 0.04215269174072911}, "guidance": ["Base todavia amplia (contraccion 18.3%, objetivo <=7%)."], "acted": 0}, {"id": 24, "ts": "2026-04-15T22:48:54", "scan_date": "2026-04-15", "symbol": "CE", "setup_type": "breakout", "status": "near", "score": 0.65, "metrics": {"avance_3m": 0.3791977811348015, "contraccion_10d": 0.152634026814969, "dist_ema10": 0.008339198781457391}, "guidance": ["Base todavia amplia (contraccion 15.3%, objetivo <=7%)."], "acted": 0}, {"id": 25, "ts": "2026-04-15T22:48:54", "scan_date": "2026-04-15", "symbol": "CGNX", "setup_type": "breakout", "status": "near", "score": 0.65, "metrics": {"avance_3m": 0.3659761453977006, "contraccion_10d": 0.17624453103379134, "dist_ema10": 0.030527077137019187}, "guidance": ["Base todavia amplia (contraccion 17.6%, objetivo <=7%)."], "acted": 0}, {"id": 26, "ts": "2026-04-15T22:48:54", "scan_date": "2026-04-15", "symbol": "CRS", "setup_type": "breakout", "status": "near", "score": 0.65, "metrics": {"avance_3m": 0.3279139352479947, "contraccion_10d": 0.1582102904327641, "dist_ema10": 0.01707842128548509}, "guidance": ["Base todavia amplia (contraccion 15.8%, objetivo <=7%)."], "acted": 0}, {"id": 27, "ts": "2026-04-15T22:48:54", "scan_date": "2026-04-15", "symbol": "ECG", "setup_type": "breakout", "status": "near", "score": 0.65, "metrics": {"avance_3m": 0.4846421430670078, "contraccion_10d": 0.15450730622632616, "dist_ema10": 0.00871472266342277}, "guidance": ["Base todavia amplia (contraccion 15.5%, objetivo <=7%)."], "acted": 0}, {"id": 28, "ts": "2026-04-15T22:48:54", "scan_date": "2026-04-15", "symbol": "ENTG", "setup_type": "breakout", "status": "near", "score": 0.65, "metrics": {"avance_3m": 0.3172145387227685, "contraccion_10d": 0.20394913001676077, "dist_ema10": 0.05329695531103007}, "guidance": ["Base todavia amplia (contraccion 20.4%, objetivo <=7%)."], "acted": 0}, {"id": 29, "ts": "2026-04-15T22:48:54", "scan_date": "2026-04-15", "symbol": "ESI", "setup_type": "breakout", "status": "near", "score": 0.65, "metrics": {"avance_3m": 0.3391155949151996, "contraccion_10d": 0.14601661431325688, "dist_ema10": 0.028088705510817658}, "guidance": ["Base todavia amplia (contraccion 14.6%, objetivo <=7%)."], "acted": 0}, {"id": 70, "ts": "2026-04-15T22:48:57", "scan_date": "2026-04-15", "symbol": "FCX", "setup_type": "vcp", "status": "near", "score": 0.65, "metrics": {"avance_previo": 0.659, "t1_pullback": 0.2043, "t2_pullback": 0.147, "t3_pullback": 0.2062, "vol_drying_ratio": 0.83, "pct_from_pivot": -0.0151, "final_tightness": 0.07, "base_days": 35}, "guidance": ["Solo 2 contracciones detectadas; ideal son 3.", "Volumen bajando pero no lo suficiente.", "Consolidacion final amplia (7.0%, objetivo <=4%)."], "acted": 0}, {"id": 71, "ts": "2026-04-15T22:48:57", "scan_date": "2026-04-15", "symbol": "CBOE", "setup_type": "vcp", "status": "near", "score": 0.63, "metrics": {"avance_previo": 0.205, "t1_pullback": 0.0871, "t2_pullback": 0.0816, "t3_pullback": 0.0905, "vol_drying_ratio": 0.74, "pct_from_pivot": -0.0023, "final_tightness": 0.0414, "base_days": 32}, "guidance": ["Avance previo insuficiente (20.5%, objetivo >=30%).", "Solo 2 contracciones detectadas; ideal son 3."], "acted": 0}, {"id": 72, "ts": "2026-04-15T22:48:57", "scan_date": "2026-04-15", "symbol": "JBHT", "setup_type": "vcp", "status": "near", "score": 0.63, "metrics": {"avance_previo": 0.261, "t1_pullback": 0.1782, "t2_pullback": 0.0756, "t3_pullback": 0.0903, "vol_drying_ratio": 0.75, "pct_from_pivot": -0.0501, "final_tightness": 0.0376, "base_days": 30}, "guidance": ["Avance previo insuficiente (26.1%, objetivo >=30%).", "Solo 2 contracciones detectadas; ideal son 3.", "A 5.0% del pivot. Acercandose."], "acted": 0}, {"id": 73, "ts": "2026-04-15T22:48:57", "scan_date": "2026-04-15", "symbol": "ON", "setup_type": "vcp", "status": "near", "score": 0.63, "metrics": {"avance_previo": 0.599, "t1_pullback": 0.2324, "t2_pullback": 0.1269, "t3_pullback": 0.2373, "vol_drying_ratio": 1.01, "pct_from_pivot": -0.018, "final_tightness": 0.0642, "base_days": 40}, "guidance": ["Solo 2 contracciones detectadas; ideal son 3.", "Volumen no se seca (ratio 1.01, objetivo <=0.75)."], "acted": 0}, {"id": 30, "ts": "2026-04-15T22:48:54", "scan_date": "2026-04-15", "symbol": "CSX", "setup_type": "breakout", "status": "near", "score": 0.6, "metrics": {"avance_3m": 0.16745851183039218, "contraccion_10d": 0.06342038635907701, "dist_ema10": 0.006809625511639883}, "guidance": ["Impulso insuficiente (actual 16.7%, objetivo >=30%)."], "acted": 0}, {"id": 31, "ts": "2026-04-15T22:48:54", "scan_date": "2026-04-15", "symbol": "ETR", "setup_type": "breakout", "status": "near", "score": 0.6, "metrics": {"avance_3m": 0.21578164432474956, "contraccion_10d": 0.05219660860627584, "dist_ema10": 0.006484318358086716}, "guidance": ["Impulso insuficiente (actual 21.6%, objetivo >=30%)."], "acted": 0}, {"id": 32, "ts": "2026-04-15T22:48:54", "scan_date": "2026-04-15", "symbol": "ROST", "setup_type": "breakout", "status": "near", "score": 0.6, "metrics": {"avance_3m": 0.1709657388416681, "contraccion_10d": 0.051349519608514534, "dist_ema10": 0.014179502084500362}, "guidance": ["Impulso insuficiente (actual 17.1%, objetivo >=30%)."], "acted": 0}, {"id": 33, "ts": "2026-04-15T22:48:54", "scan_date": "2026-04-15", "symbol": "TGT", "setup_type": "breakout", "status": "near", "score": 0.6, "metrics": {"avance_3m": 0.13020978770692526, "contraccion_10d": 0.06209812877724721, "dist_ema10": 0.017648606491173613}, "guidance": ["Impulso insuficiente (actual 13.0%, objetivo >=30%)."], "acted": 0}, {"id": 34, "ts": "2026-04-15T22:48:54", "scan_date": "2026-04-15", "symbol": "BURL", "setup_type": "breakout", "status": "near", "score": 0.6, "metrics": {"avance_3m": 0.11814355414717559, "contraccion_10d": 0.06488799815311079, "dist_ema10": 0.020274549837191014}, "guidance": ["Impulso insuficiente (actual 11.8%, objetivo >=30%)."], "acted": 0}, {"id": 35, "ts": "2026-04-15T22:48:54", "scan_date": "2026-04-15", "symbol": "CWEN", "setup_type": "breakout", "status": "near", "score": 0.6, "metrics": {"avance_3m": 0.22991588508586425, "contraccion_10d": 0.05761111667375075, "dist_ema10": 0.005270134089552014}, "guidance": ["Impulso insuficiente (actual 23.0%, objetivo >=30%)."], "acted": 0}, {"id": 36, "ts": "2026-04-15T22:48:54", "scan_date": "2026-04-15", "symbol": "AUR", "setup_type": "ep", "status": "near", "score": 0.6, "metrics": {"gap_pct": 0.012526726364908036, "gap_close": 0.13490366255858355, "vol_ratio": 1.582768685930117, "rango_dia": 0.11415094288696638}, "guidance": ["Gap inicial corto (1.3%, objetivo >=10%)."], "acted": 0}, {"id": 74, "ts": "2026-04-15T22:48:57", "scan_date": "2026-04-15", "symbol": "DE", "setup_type": "vcp", "status": "near", "score": 0.6, "metrics": {"avance_previo": 0.42, "t1_pullback": 0.1432, "t2_pullback": 0.0768, "t3_pullback": 0.1035, "vol_drying_ratio": 0.73, "pct_from_pivot": -0.1422, "final_tightness": 0.0817, "base_days": 39}, "guidance": ["Solo 2 contracciones detectadas; ideal son 3.", "Lejos del pivot (-14.2% del maximo).", "Consolidacion final amplia (8.2%, objetivo <=4%)."], "acted": 0}, {"id": 75, "ts": "2026-04-15T22:48:57", "scan_date": "2026-04-15", "symbol": "XOM", "setup_type": "vcp", "status": "near", "score": 0.6, "metrics": {"avance_previo": 0.476, "t1_pullback": 0.0957, "t2_pullback": 0.0865, "t3_pullback": 0.0476, "vol_drying_ratio": 0.77, "pct_from_pivot": -0.1553, "final_tightness": 0.084, "base_days": 12}, "guidance": ["Volumen bajando pero no lo suficiente.", "Lejos del pivot (-15.5% del maximo).", "Consolidacion final amplia (8.4%, objetivo <=4%)."], "acted": 0}, {"id": 76, "ts": "2026-04-15T22:48:57", "scan_date": "2026-04-15", "symbol": "AU", "setup_type": "vcp", "status": "near", "score": 0.6, "metrics": {"avance_previo": 0.54, "t1_pullback": 0.2585, "t2_pullback": 0.1398, "t3_pullback": 0.1868, "vol_drying_ratio": 0.7, "pct_from_pivot": -0.1774, "final_tightness": 0.0752, "base_days": 32}, "guidance": ["Solo 2 contracciones detectadas; ideal son 3.", "Lejos del pivot (-17.7% del maximo).", "Consolidacion final amplia (7.5%, objetivo <=4%)."], "acted": 0}, {"id": 77, "ts": "2026-04-15T22:48:57", "scan_date": "2026-04-15", "symbol": "BPOP", "setup_type": "vcp", "status": "near", "score": 0.6, "metrics": {"avance_previo": 0.299, "t1_pullback": 0.1101, "t2_pullback": 0.0822, "t3_pullback": 0.1231, "vol_drying_ratio": 0.89, "pct_from_pivot": -0.0236, "final_tightness": 0.0355, "base_days": 44}, "guidance": ["Avance previo insuficiente (29.9%, objetivo >=30%).", "Solo 2 contracciones detectadas; ideal son 3.", "Volumen bajando pero no lo suficiente."], "acted": 0}, {"id": 78, "ts": "2026-04-15T22:48:57", "scan_date": "2026-04-15", "symbol": "FTAI", "setup_type": "vcp", "status": "near", "score": 0.6, "metrics": {"avance_previo": 0.867, "t1_pullback": 0.2683, "t2_pullback": 0.1132, "t3_pullback": 0.1534, "vol_drying_ratio": 0.48, "pct_from_pivot": -0.1645, "final_tightness": 0.1103, "base_days": 34}, "guidance": ["Solo 2 contracciones detectadas; ideal son 3.", "Lejos del pivot (-16.5% del maximo).", "Consolidacion final amplia (11.0%, objetivo <=4%)."], "acted": 0}, {"id": 79, "ts": "2026-04-15T22:48:57", "scan_date": "2026-04-15", "symbol": "ALGN", "setup_type": "vcp", "status": "near", "score": 0.58, "metrics": {"avance_previo": 0.452, "t1_pullback": 0.1191, "t2_pullback": 0.0999, "t3_pullback": 0.1216, "vol_drying_ratio": 0.83, "pct_from_pivot": -0.0629, "final_tightness": 0.0955, "base_days": 43}, "guidance": ["Solo 2 contracciones detectadas; ideal son 3.", "Volumen bajando pero no lo suficiente.", "A 6.3% del pivot. Acercandose.", "Consolidacion final amplia (9.5%, objetivo <=4%)."], "acted": 0}, {"id": 80, "ts": "2026-04-15T22:48:57", "scan_date": "2026-04-15", "symbol": "GNRC", "setup_type": "vcp", "status": "near", "score": 0.58, "metrics": {"avance_previo": 0.62, "t1_pullback": 0.1966, "t2_pullback": 0.1168, "t3_pullback": 0.1076, "vol_drying_ratio": 1.05, "pct_from_pivot": -0.1522, "final_tightness": 0.0617, "base_days": 35}, "guidance": ["Volumen no se seca (ratio 1.05, objetivo <=0.75).", "Lejos del pivot (-15.2% del maximo)."], "acted": 0}, {"id": 81, "ts": "2026-04-15T22:48:57", "scan_date": "2026-04-15", "symbol": "ATI", "setup_type": "vcp", "status": "near", "score": 0.56, "metrics": {"avance_previo": 0.704, "t1_pullback": 0.168, "t2_pullback": 0.0731, "t3_pullback": 0.171, "vol_drying_ratio": 0.9, "pct_from_pivot": -0.0673, "final_tightness": 0.059, "base_days": 32}, "guidance": ["Solo 2 contracciones detectadas; ideal son 3.", "Volumen no se seca (ratio 0.90, objetivo <=0.75).", "A 6.7% del pivot. Acercandose."], "acted": 0}, {"id": 82, "ts": "2026-04-15T22:48:57", "scan_date": "2026-04-15", "symbol": "GOOGL", "setup_type": "vcp", "status": "near", "score": 0.55, "metrics": {"avance_previo": 0.228, "t1_pullback": 0.1511, "t2_pullback": 0.054, "t3_pullback": 0.1433, "vol_drying_ratio": 0.71, "pct_from_pivot": -0.0334, "final_tightness": 0.0784, "base_days": 50}, "guidance": ["Avance previo insuficiente (22.8%, objetivo >=30%).", "Solo 2 contracciones detectadas; ideal son 3.", "Consolidacion final amplia (7.8%, objetivo <=4%)."], "acted": 0}, {"id": 83, "ts": "2026-04-15T22:48:57", "scan_date": "2026-04-15", "symbol": "ASML", "setup_type": "vcp", "status": "near", "score": 0.55, "metrics": {"avance_previo": 0.488, "t1_pullback": 0.1752, "t2_pullback": 0.079, "t3_pullback": 0.1644, "vol_drying_ratio": 1.24, "pct_from_pivot": -0.0423, "final_tightness": 0.0809, "base_days": 35}, "guidance": ["Solo 2 contracciones detectadas; ideal son 3.", "Volumen no se seca (ratio 1.24, objetivo <=0.75).", "Consolidacion final amplia (8.1%, objetivo <=4%)."], "acted": 0}, {"id": 84, "ts": "2026-04-15T22:48:57", "scan_date": "2026-04-15", "symbol": "ENTG", "setup_type": "vcp", "status": "near", "score": 0.55, "metrics": {"avance_previo": 0.935, "t1_pullback": 0.2411, "t2_pullback": 0.118, "t3_pullback": 0.2356, "vol_drying_ratio": 0.94, "pct_from_pivot": -0.0386, "final_tightness": 0.0983, "base_days": 36}, "guidance": ["Solo 2 contracciones detectadas; ideal son 3.", "Volumen no se seca (ratio 0.94, objetivo <=0.75).", "Consolidacion final amplia (9.8%, objetivo <=4%)."], "acted": 0}, {"id": 85, "ts": "2026-04-15T22:48:57", "scan_date": "2026-04-15", "symbol": "HLT", "setup_type": "vcp", "status": "near", "score": 0.53, "metrics": {"avance_previo": 0.239, "t1_pullback": 0.1133, "t2_pullback": 0.0556, "t3_pullback": 0.1174, "vol_drying_ratio": 0.78, "pct_from_pivot": -0.0144, "final_tightness": 0.0501, "base_days": 43}, "guidance": ["Avance previo insuficiente (23.9%, objetivo >=30%).", "Solo 2 contracciones detectadas; ideal son 3.", "Volumen bajando pero no lo suficiente."], "acted": 0}, {"id": 86, "ts": "2026-04-15T22:48:57", "scan_date": "2026-04-15", "symbol": "MAR", "setup_type": "vcp", "status": "near", "score": 0.53, "metrics": {"avance_previo": 0.298, "t1_pullback": 0.1319, "t2_pullback": 0.0619, "t3_pullback": 0.1375, "vol_drying_ratio": 0.87, "pct_from_pivot": -0.015, "final_tightness": 0.0627, "base_days": 43}, "guidance": ["Avance previo insuficiente (29.8%, objetivo >=30%).", "Solo 2 contracciones detectadas; ideal son 3.", "Volumen bajando pero no lo suficiente."], "acted": 0}, {"id": 44, "ts": "2026-04-15T22:48:55", "scan_date": "2026-04-15", "symbol": "AMD", "setup_type": "parabolic", "status": "near", "score": 0.5, "metrics": {"avance_10d": 0.22791487975419855, "avance_5d": 0.09077077325448424, "dist_ema10": 0.0870385069720867, "dias_up": 10.0, "racha_max": 11.0}, "guidance": ["Falta aceleracion (avance 10d 22.8%, objetivo >=25%).", "Impulso corto plazo flojo (avance 5d 9.1%, objetivo >=15%)."], "acted": 0}, {"id": 87, "ts": "2026-04-15T22:48:57", "scan_date": "2026-04-15", "symbol": "CSX", "setup_type": "vcp", "status": "near", "score": 0.5, "metrics": {"avance_previo": 0.244, "t1_pullback": 0.101, "t2_pullback": 0.0595, "t3_pullback": 0.0775, "vol_drying_ratio": 0.93, "pct_from_pivot": -0.0288, "final_tightness": 0.0296, "base_days": 32}, "guidance": ["Avance previo insuficiente (24.4%, objetivo >=30%).", "Solo 2 contracciones detectadas; ideal son 3.", "Volumen no se seca (ratio 0.93, objetivo <=0.75)."], "acted": 0}, {"id": 88, "ts": "2026-04-15T22:48:57", "scan_date": "2026-04-15", "symbol": "ALGM", "setup_type": "vcp", "status": "near", "score": 0.5, "metrics": {"avance_previo": 0.775, "t1_pullback": 0.2367, "t2_pullback": 0.1141, "t3_pullback": 0.2531, "vol_drying_ratio": 0.78, "pct_from_pivot": -0.1507, "final_tightness": 0.0792, "base_days": 43}, "guidance": ["Solo 2 contracciones detectadas; ideal son 3.", "Volumen bajando pero no lo suficiente.", "Lejos del pivot (-15.1% del maximo).", "Consolidacion final amplia (7.9%, objetivo <=4%)."], "acted": 0}, {"id": 89, "ts": "2026-04-15T22:48:57", "scan_date": "2026-04-15", "symbol": "DOW", "setup_type": "vcp", "status": "near", "score": 0.46, "metrics": {"avance_previo": 0.782, "t1_pullback": 0.0738, "t2_pullback": 0.1474, "t3_pullback": 0.0636, "vol_drying_ratio": 0.88, "pct_from_pivot": -0.0912, "final_tightness": 0.07, "base_days": 11}, "guidance": ["Contracciones no decrecientes: T1=7.4%, T2=14.7%, T3=6.4%.", "Volumen bajando pero no lo suficiente.", "A 9.1% del pivot. Acercandose."], "acted": 0}, {"id": 90, "ts": "2026-04-15T22:48:57", "scan_date": "2026-04-15", "symbol": "JCI", "setup_type": "vcp", "status": "near", "score": 0.46, "metrics": {"avance_previo": 0.26, "t1_pullback": 0.121, "t2_pullback": 0.0683, "t3_pullback": 0.1174, "vol_drying_ratio": 0.82, "pct_from_pivot": -0.0605, "final_tightness": 0.0529, "base_days": 35}, "guidance": ["Avance previo insuficiente (26.0%, objetivo >=30%).", "Solo 2 contracciones detectadas; ideal son 3.", "Volumen bajando pero no lo suficiente.", "A 6.0% del pivot. Acercandose."], "acted": 0}, {"id": 91, "ts": "2026-04-15T22:48:57", "scan_date": "2026-04-15", "symbol": "AVGO", "setup_type": "vcp", "status": "near", "score": 0.45, "metrics": {"avance_previo": 0.218, "t1_pullback": 0.2248, "t2_pullback": 0.1378, "t3_pullback": 0.2201, "vol_drying_ratio": 0.76, "pct_from_pivot": -0.0393, "final_tightness": 0.1149, "base_days": 86}, "guidance": ["Avance previo insuficiente (21.8%, objetivo >=30%).", "Solo 2 contracciones detectadas; ideal son 3.", "Volumen bajando pero no lo suficiente.", "Consolidacion final amplia (11.5%, objetivo <=4%)."], "acted": 0}]